dbt/adapters/watsonx_spark/__init__.py
dbt/adapters/watsonx_spark/__version__.py
dbt/adapters/watsonx_spark/column.py
dbt/adapters/watsonx_spark/connections.py
dbt/adapters/watsonx_spark/impl.py
dbt/adapters/watsonx_spark/python_submissions.py
dbt/adapters/watsonx_spark/relation.py
dbt/adapters/watsonx_spark/session.py
dbt/adapters/watsonx_spark/http_auth/__init__.py
dbt/adapters/watsonx_spark/http_auth/authenticator.py
dbt/adapters/watsonx_spark/http_auth/exceptions.py
dbt/adapters/watsonx_spark/http_auth/status_codes.py
dbt/adapters/watsonx_spark/http_auth/wxd_authenticator.py
dbt/include/watsonx_spark/__init__.py
dbt/include/watsonx_spark/dbt_project.yml
dbt/include/watsonx_spark/profile_template.yml
dbt/include/watsonx_spark/macros/adapters.sql
dbt/include/watsonx_spark/macros/apply_grants.sql
dbt/include/watsonx_spark/macros/materializations/clone.sql
dbt/include/watsonx_spark/macros/materializations/seed.sql
dbt/include/watsonx_spark/macros/materializations/snapshot.sql
dbt/include/watsonx_spark/macros/materializations/table.sql
dbt/include/watsonx_spark/macros/materializations/view.sql
dbt/include/watsonx_spark/macros/materializations/incremental/column_helpers.sql
dbt/include/watsonx_spark/macros/materializations/incremental/incremental.sql
dbt/include/watsonx_spark/macros/materializations/incremental/strategies.sql
dbt/include/watsonx_spark/macros/materializations/incremental/validate.sql
dbt/include/watsonx_spark/macros/utils/any_value.sql
dbt/include/watsonx_spark/macros/utils/array_append.sql
dbt/include/watsonx_spark/macros/utils/array_concat.sql
dbt/include/watsonx_spark/macros/utils/array_construct.sql
dbt/include/watsonx_spark/macros/utils/assert_not_null.sql
dbt/include/watsonx_spark/macros/utils/bool_or.sql
dbt/include/watsonx_spark/macros/utils/concat.sql
dbt/include/watsonx_spark/macros/utils/date.sql
dbt/include/watsonx_spark/macros/utils/dateadd.sql
dbt/include/watsonx_spark/macros/utils/datediff.sql
dbt_watsonx_spark-0.1.1.dist-info/licenses/LICENSE
dbt_watsonx_spark-0.1.1.dist-info/licenses/NOTICES
dbt_watsonx_spark-0.1.1.dist-info/METADATA
dbt_watsonx_spark-0.1.1.dist-info/WHEEL
dbt_watsonx_spark-0.1.1.dist-info/top_level.txt
dbt_watsonx_spark-0.1.1.dist-info/RECORD
