Metadata-Version: 2.4
Name: dbt-watsonx-spark
Version: 0.1.1
Summary: IBM watsonx.data spark plugin for dbt
Home-page: https://github.com/IBM/dbt-watsonx-spark
Author: IBM watsonx.data
Classifier: Development Status :: 5 - Production/Stable
Classifier: License :: OSI Approved :: Apache Software License
Classifier: Operating System :: Microsoft :: Windows
Classifier: Operating System :: MacOS :: MacOS X
Classifier: Operating System :: POSIX :: Linux
Classifier: Programming Language :: Python :: 3.9
Classifier: Programming Language :: Python :: 3.10
Classifier: Programming Language :: Python :: 3.11
Classifier: Programming Language :: Python :: 3.12
Requires-Python: >=3.8
License-File: LICENSE
License-File: NOTICES
Requires-Dist: sqlparams>=3.0.0
Requires-Dist: dbt-common<2.0,>=1.0.4
Requires-Dist: dbt-adapters<2.0,>=1.1.1
Requires-Dist: dbt-core>=1.8.0
Requires-Dist: PyHive[hive_pure_sasl]~=0.7.0
Requires-Dist: thrift>=0.20.0
Requires-Dist: requests>=2.32.2
Dynamic: author
Dynamic: classifier
Dynamic: description
Dynamic: description-content-type
Dynamic: home-page
Dynamic: license-file
Dynamic: requires-dist
Dynamic: requires-python
Dynamic: summary
